freeza/__init__.py
freeza/spark_commit_offset.py
freeza/version.py
freeza_offset-1.0.10.dist-info/LICENSE
freeza_offset-1.0.10.dist-info/METADATA
freeza_offset-1.0.10.dist-info/WHEEL
freeza_offset-1.0.10.dist-info/top_level.txt
freeza_offset-1.0.10.dist-info/RECORD
